flask_githubapp/__init__.py
flask_githubapp/core.py
flask_githubapp/version.py
Flask_GitHubApp-0.2.0.dist-info/LICENSE
Flask_GitHubApp-0.2.0.dist-info/METADATA
Flask_GitHubApp-0.2.0.dist-info/WHEEL
Flask_GitHubApp-0.2.0.dist-info/top_level.txt
Flask_GitHubApp-0.2.0.dist-info/RECORD
