Metadata-Version: 2.1
Name: Flask-GitHubApp
Version: 0.2.0
Summary: Rapid GitHub app development in Python
Home-page: https://github.com/bradshjg/flask-githubapp
Author: Jimmy Bradshaw
Author-email: james.g.bradshaw@gmail.com
License: MIT
Platform: any
Classifier: License :: OSI Approved :: MIT License
Classifier: Framework :: Flask
Classifier: Programming Language :: Python
Classifier: Programming Language :: Python :: 3.5
Classifier: Programming Language :: Python :: 3.6
Classifier: Programming Language :: Python :: 3.7
Classifier: Environment :: Web Environment
Classifier: Intended Audience :: Developers
Classifier: Operating System :: OS Independent
Classifier: Topic :: Internet :: WWW/HTTP :: Dynamic Content
Classifier: Topic :: Software Development :: Libraries :: Python Modules
Requires-Dist: flask
Requires-Dist: github3.py
